setup.py
django_xenforo.egg-info/PKG-INFO
django_xenforo.egg-info/SOURCES.txt
django_xenforo.egg-info/dependency_links.txt
django_xenforo.egg-info/not-zip-safe
django_xenforo.egg-info/requires.txt
django_xenforo.egg-info/top_level.txt
xenforo/__init__.py
xenforo/admin.py
xenforo/context_processors.py
xenforo/middleware.py
xenforo/models.py
xenforo/tests.py
xenforo/user_backend.py
xenforo/utils.py
xenforo/views.py
xenforo/migrations/0001_initial.py
xenforo/migrations/__init__.py